{
    "fluentMethods": true,
    "clientRootFolder": "",
    "relationships": [],
    "fields": [
        {
            "fieldName": "dateCreated",
            "fieldType": "Instant"
        },
        {
            "fieldName": "dateUpdated",
            "fieldType": "Instant",
            "fieldValidateRules": [
                "required"
            ]
        },
        {
            "fieldName": "type",
            "fieldType": "String",
            "fieldValidateRules": [
                "required"
            ]
        }
    ],
    "changelogDate": "20181113114722",
    "dto": "mapstruct",
    "searchEngine": false,
    "service": "serviceImpl",
    "entityTableName": "product_type",
    "jpaMetamodelFiltering": false,
    "pagination": "pagination"
}
